{
    "positions": {
        "no": { "x": 1366, "y": 2127, "font": "Helvetica-Bold", "fontSize": 35 },
        "date": { "x": 1366, "y": 2065, "font": "Helvetica", "fontSize": 28 },
        "name": { "x": 355, "y": 2065, "font": "Helvetica-Bold", "fontSize": 35 },
        "email": { "x": 355, "y": 2045, "font": "Helvetica", "fontSize": 35 },
        "items": {
            "no": { "x": 200, "font": "Helvetica", "fontSize": 28 },
            "description": { "x": 310, "font": "Helvetica", "fontSize": 28 },
            "quantity": { "x": 1000, "font": "Helvetica", "fontSize": 28 },
            "price": { "x": 1230, "font": "Helvetica", "fontSize": 28 },
            "amount": { "x": 1500, "font": "Helvetica", "fontSize": 28 },
            "startY": 1740,
            "lineSpacing": 20
        },
        "tax": { "x": 50, "y": 120, "font": "Helvetica-Bold", "fontSize": 12 },
        "totals": { "x": 400, "y": 100, "font": "Helvetica-Bold", "fontSize": 14 }
    },
    "settings": {
        "itemsPerPage": 10
    }
}
